hodgelaplacians/__init__.py
hodgelaplacians/hodgelaplacians.py
hodgelaplacians-0.1.dist-info/LICENSE
hodgelaplacians-0.1.dist-info/METADATA
hodgelaplacians-0.1.dist-info/NOTICE
hodgelaplacians-0.1.dist-info/WHEEL
hodgelaplacians-0.1.dist-info/top_level.txt
hodgelaplacians-0.1.dist-info/RECORD
